miss__Lightgbm_mmlspark/__init__.py
miss__Lightgbm_mmlspark/automl/FindBestModel.py
miss__Lightgbm_mmlspark/automl/HyperparamBuilder.py
miss__Lightgbm_mmlspark/automl/TuneHyperparameters.py
miss__Lightgbm_mmlspark/automl/_FindBestModel.py
miss__Lightgbm_mmlspark/automl/_TuneHyperparameters.py
miss__Lightgbm_mmlspark/automl/__init__.py
miss__Lightgbm_mmlspark/cntk/CNTKModel.py
miss__Lightgbm_mmlspark/cntk/_CNTKModel.py
miss__Lightgbm_mmlspark/cntk/__init__.py
miss__Lightgbm_mmlspark/cognitive/AddDocuments.py
miss__Lightgbm_mmlspark/cognitive/AnalyzeImage.py
miss__Lightgbm_mmlspark/cognitive/AzureSearchWriter.py
miss__Lightgbm_mmlspark/cognitive/BingImageSearch.py
miss__Lightgbm_mmlspark/cognitive/DescribeImage.py
miss__Lightgbm_mmlspark/cognitive/DetectAnomalies.py
miss__Lightgbm_mmlspark/cognitive/DetectFace.py
miss__Lightgbm_mmlspark/cognitive/DetectLastAnomaly.py
miss__Lightgbm_mmlspark/cognitive/EntityDetector.py
miss__Lightgbm_mmlspark/cognitive/FindSimilarFace.py
miss__Lightgbm_mmlspark/cognitive/GenerateThumbnails.py
miss__Lightgbm_mmlspark/cognitive/GroupFaces.py
miss__Lightgbm_mmlspark/cognitive/IdentifyFaces.py
miss__Lightgbm_mmlspark/cognitive/KeyPhraseExtractor.py
miss__Lightgbm_mmlspark/cognitive/LanguageDetector.py
miss__Lightgbm_mmlspark/cognitive/NER.py
miss__Lightgbm_mmlspark/cognitive/OCR.py
miss__Lightgbm_mmlspark/cognitive/RecognizeDomainSpecificContent.py
miss__Lightgbm_mmlspark/cognitive/RecognizeText.py
miss__Lightgbm_mmlspark/cognitive/SimpleDetectAnomalies.py
miss__Lightgbm_mmlspark/cognitive/SpeechToText.py
miss__Lightgbm_mmlspark/cognitive/TagImage.py
miss__Lightgbm_mmlspark/cognitive/TextSentiment.py
miss__Lightgbm_mmlspark/cognitive/VerifyFaces.py
miss__Lightgbm_mmlspark/cognitive/_BingImageSearch.py
miss__Lightgbm_mmlspark/cognitive/__init__.py
miss__Lightgbm_mmlspark/core/__init__.py
miss__Lightgbm_mmlspark/core/schema/TypeConversionUtils.py
miss__Lightgbm_mmlspark/core/schema/Utils.py
miss__Lightgbm_mmlspark/core/schema/__init__.py
miss_Lightgbm_mmlspark-1.0.0.dist-info/LICENSE.txt
miss_Lightgbm_mmlspark-1.0.0.dist-info/METADATA
miss_Lightgbm_mmlspark-1.0.0.dist-info/WHEEL
miss_Lightgbm_mmlspark-1.0.0.dist-info/top_level.txt
miss_Lightgbm_mmlspark-1.0.0.dist-info/zip-safe
miss_Lightgbm_mmlspark-1.0.0.dist-info/RECORD
