Metadata-Version: 2.1
Name: miss-Lightgbm-mmlspark
Version: 1.0.0
Summary: Microsoft ML for Spark
Home-page: https://github.com/Azure/mmlspark
Author: yongming.pang
Author-email: 891067464@qq.com
License: MIT
Platform: UNKNOWN
Classifier: Programming Language :: Python :: 3
License-File: LICENSE.txt
